hlcpy/__init__.py
hlcpy/util.py
tests/unit/__init__.py
tests/unit/test_hlc.py
tests/unit/test_util.py
hlcpy-0.0.2.dist-info/LICENSE
hlcpy-0.0.2.dist-info/METADATA
hlcpy-0.0.2.dist-info/WHEEL
hlcpy-0.0.2.dist-info/top_level.txt
hlcpy-0.0.2.dist-info/RECORD
