Metadata-Version: 2.1
Name: hlcpy
Version: 0.0.2
Summary: Hybrid Logical Clock in Python
Home-page: https://github.com/konradmalik/hlcpy.git
Author: Konrad Malik
Author-email: konrad.malik@gmail.com
License: MIT
Platform: UNKNOWN
Classifier: License :: OSI Approved :: MIT License
Classifier: Programming Language :: Python :: 3
Classifier: Programming Language :: Python :: 3.7
Classifier: Programming Language :: Python :: 3.8
Classifier: Programming Language :: Python :: 3.9
Requires-Dist: iso8601 (>=0.1.14)
